axm/__init__.py
axm/typing.py
axm-1.0.2.dist-info/LICENSE.txt
axm-1.0.2.dist-info/METADATA
axm-1.0.2.dist-info/WHEEL
axm-1.0.2.dist-info/top_level.txt
axm-1.0.2.dist-info/RECORD
