Metadata-Version: 2.1
Name: axm
Version: 1.0.2
Summary: A versatile toolkit for customizable and reusable functions in Python.
License: MIT License
Project-URL: source, https://github.com/DevByEagle/axm
Project-URL: download, https://pypi.org/project/axm/#files
Project-URL: tracker, https://github.com/DevByEagle/axm/issues
Classifier: License :: OSI Approved :: MIT License
Classifier: Intended Audience :: Developers
Classifier: Programming Language :: Python :: 3
Classifier: Programming Language :: Python :: 3.10
Classifier: Programming Language :: Python :: 3.11
Classifier: Programming Language :: Python :: 3.12
Classifier: Programming Language :: Python :: 3.13
Classifier: Topic :: Software Development
License-File: LICENSE.txt
